simple_repository_browser/__init__.py
simple_repository_browser/__main__.py
simple_repository_browser/_app.py
simple_repository_browser/_search.py
simple_repository_browser/_typing_compat.py
simple_repository_browser/_version.py
simple_repository_browser/compatibility_matrix.py
simple_repository_browser/controller.py
simple_repository_browser/crawler.py
simple_repository_browser/errors.py
simple_repository_browser/fetch_description.py
simple_repository_browser/fetch_projects.py
simple_repository_browser/filesize_enrichment.py
simple_repository_browser/metadata_injector.py
simple_repository_browser/model.py
simple_repository_browser/short_release_info.py
simple_repository_browser/static_files.py
simple_repository_browser/view.py
simple_repository_browser/static/css/theme.css
simple_repository_browser/static/css/theme.variables.css
simple_repository_browser/static/images/favicon.ico
simple_repository_browser/static/images/logo-large.svg
simple_repository_browser/static/images/logo-small-single-tower.svg
simple_repository_browser/static/images/logo-small.svg
simple_repository_browser/static/images/python-logo-only.svg
simple_repository_browser/static/vendored/bootstrap.bundle.min.js
simple_repository_browser/static/vendored/bootstrap.bundle.min.js.map
simple_repository_browser/static/vendored/bootstrap.customized.js
simple_repository_browser/static/vendored/bootstrap.customized.js.LICENSE.txt
simple_repository_browser/static/vendored/bootstrap.customized.js.css
simple_repository_browser/static/vendored/fontawesome-free.all.min.js
simple_repository_browser/static/vendored/jquery.min.js
simple_repository_browser/static/vendored/popper.min.js
simple_repository_browser/templates/base/about.html
simple_repository_browser/templates/base/base.html
simple_repository_browser/templates/base/error.html
simple_repository_browser/templates/base/index.html
simple_repository_browser/templates/base/page.html
simple_repository_browser/templates/base/project.html
simple_repository_browser-0.10.0.dist-info/licenses/LICENSE
simple_repository_browser-0.10.0.dist-info/METADATA
simple_repository_browser-0.10.0.dist-info/WHEEL
simple_repository_browser-0.10.0.dist-info/entry_points.txt
simple_repository_browser-0.10.0.dist-info/top_level.txt
simple_repository_browser-0.10.0.dist-info/RECORD
