Metadata-Version: 2.4
Name: simple-repository-browser
Version: 0.10.0
Summary: A web interface to browse and search packages in any simple package repository (PEP-503), inspired by PyPI / warehouse
Author: Phil Elson, Francesco Iannaccone, Ivan Sinkarenko
Project-URL: Homepage, https://github.com/simple-repository/simple-repository-browser
Requires-Python: >=3.11
License-File: LICENSE
Requires-Dist: httpx
Requires-Dist: aiosqlite
Requires-Dist: diskcache
Requires-Dist: docutils
Requires-Dist: fastapi
Requires-Dist: importlib_metadata>=6.0
Requires-Dist: jinja2
Requires-Dist: markdown
Requires-Dist: markupsafe
Requires-Dist: packaging
Requires-Dist: parsley
Requires-Dist: pkginfo>=1.12
Requires-Dist: readme-renderer[md]
Requires-Dist: simple-repository~=0.10
Requires-Dist: typing-extensions
Requires-Dist: uvicorn
Requires-Dist: authlib
Requires-Dist: starlette[full]
Provides-Extra: test
Requires-Dist: pytest; extra == "test"
Requires-Dist: pytest-asyncio; extra == "test"
Provides-Extra: dev
Requires-Dist: simple-repository-browser[test]; extra == "dev"
Dynamic: license-file
